chatformers/__init__.py
chatformers/chatbot.py
chatformers/chatformers_constants.py
chatformers-1.0.8.dist-info/LICENSE
chatformers-1.0.8.dist-info/LICENSE.txt
chatformers-1.0.8.dist-info/METADATA
chatformers-1.0.8.dist-info/WHEEL
chatformers-1.0.8.dist-info/top_level.txt
chatformers-1.0.8.dist-info/RECORD
