Metadata-Version: 2.1
Name: chatformers
Version: 1.0.8
Summary: Chatformers is a Python package that simplifies chatbot development by automatically managing chat history using local vector databases like Chroma DB.
Home-page: https://github.com/Dipeshpal/chatformers
Author: Dipesh Paul
Author-email: dipeshpal17@gmail.com
Classifier: Programming Language :: Python :: 3
Classifier: License :: OSI Approved :: MIT License
Classifier: Operating System :: OS Independent
Requires-Python: >=3.9
License-File: LICENSE
License-File: LICENSE.txt
Requires-Dist: ollama==0.3.3
Requires-Dist: openai==1.51.2
Requires-Dist: lazyme==0.0.27
Requires-Dist: chromadb==0.5.3
Requires-Dist: tqdm==4.66.5
Requires-Dist: mem0ai==0.1.19
Requires-Dist: groq==0.11.0
